guindex/__init__.py
guindex/guindex_constants.py
guindex/guindex_functions.py
guindex-0.0.3.dist-info/LICENSE
guindex-0.0.3.dist-info/METADATA
guindex-0.0.3.dist-info/WHEEL
guindex-0.0.3.dist-info/top_level.txt
guindex-0.0.3.dist-info/RECORD
