Metadata-Version: 2.1
Name: guindex
Version: 0.0.3
Summary: A package to retrieve data from the Guindex project.
Author-email: The Guindex Team <theguindexteam@gmail.com>
License: MIT License
Project-URL: repository, https://github.com/rmcg123/guindex-py
Classifier: Programming Language :: Python :: 3
Classifier: License :: OSI Approved :: MIT License
Classifier: Operating System :: OS Independent
Requires-Python: >=3.8
License-File: LICENSE
Requires-Dist: requests
Requires-Dist: pandas
